click_tree/__init__.py
click_tree-0.0.1.dist-info/LICENSE
click_tree-0.0.1.dist-info/METADATA
click_tree-0.0.1.dist-info/WHEEL
click_tree-0.0.1.dist-info/top_level.txt
click_tree-0.0.1.dist-info/RECORD
