Metadata-Version: 2.1
Name: click-tree
Version: 0.0.1
Summary: automatically generate a tree view of a click CLI
Home-page: https://github.com/adammillerio/click-tree
Download-URL: https://github.com/adammillerio/click-tree/archive/v0.0.1.tar.gz
Author: Adam Miller
Author-email: miller@adammiller.io
License: MIT
Classifier: Development Status :: 5 - Production/Stable
Classifier: Intended Audience :: Developers
Classifier: License :: OSI Approved :: MIT License
Classifier: Programming Language :: Python :: 3
Classifier: Programming Language :: Python :: 3.10
Classifier: Programming Language :: Python :: 3.11
Classifier: Programming Language :: Python :: 3.12
Classifier: Programming Language :: Python :: 3 :: Only
License-File: LICENSE
Requires-Dist: anytree
Requires-Dist: click
Provides-Extra: dev
Requires-Dist: black ; extra == 'dev'
Requires-Dist: pyre-check ; extra == 'dev'
Requires-Dist: testslide ; extra == 'dev'
